{
	"configurations" : 
	[
		{
			"directories" : 
			[
				{
					"build" : ".",
					"jsonFile" : "directory-.-Debug-f5ebdc15457944623624.json",
					"minimumCMakeVersion" : 
					{
						"string" : "3.16"
					},
					"projectIndex" : 0,
					"source" : ".",
					"targetIndexes" : 
					[
						0,
						1,
						2
					]
				}
			],
			"name" : "Debug",
			"projects" : 
			[
				{
					"directoryIndexes" : 
					[
						0
					],
					"name" : "Open_gl",
					"targetIndexes" : 
					[
						0,
						1,
						2
					]
				}
			],
			"targets" : 
			[
				{
					"directoryIndex" : 0,
					"id" : "Open_gl::@6890427a1f51a3e7e1df",
					"jsonFile" : "target-Open_gl-Debug-aaa8b64b4cd7188ea603.json",
					"name" : "Open_gl",
					"projectIndex" : 0
				},
				{
					"directoryIndex" : 0,
					"id" : "Open_gl_autogen::@6890427a1f51a3e7e1df",
					"jsonFile" : "target-Open_gl_autogen-Debug-485d4c3f0868800bbb0b.json",
					"name" : "Open_gl_autogen",
					"projectIndex" : 0
				},
				{
					"directoryIndex" : 0,
					"id" : "Open_gl_autogen_timestamp_deps::@6890427a1f51a3e7e1df",
					"jsonFile" : "target-Open_gl_autogen_timestamp_deps-Debug-906bdd69ccbc6b01348e.json",
					"name" : "Open_gl_autogen_timestamp_deps",
					"projectIndex" : 0
				}
			]
		}
	],
	"kind" : "codemodel",
	"paths" : 
	{
		"build" : "/home/ibhou/Documents/OpenGL/OpenGL_API_V6/build",
		"source" : "/home/ibhou/Documents/OpenGL/OpenGL_API_V6"
	},
	"version" : 
	{
		"major" : 2,
		"minor" : 6
	}
}
